tests/__init__.py
tests/test_addresses.py
tests/test_blockchain.py
tests/test_client.py
tests/test_config.py
tests/test_db.py
tests/test_grpc_client.py
tests/test_restore.py
tests/test_storage.py
tests/test_transfer.py
tests/test_utils.py
tests/test_wallet.py
tests/crypt/__init__.py
tests/crypt/test_address.py
tests/crypt/test_bip39.py
tests/crypt/test_crypt.py
tests/crypt/test_keys.py
transferchain/__init__.py
transferchain/addresses.py
transferchain/blockchain.py
transferchain/cert.py
transferchain/client.py
transferchain/config.py
transferchain/constants.py
transferchain/datastructures.py
transferchain/db.py
transferchain/exceptions.py
transferchain/grpc_client.py
transferchain/logger.py
transferchain/mixins.py
transferchain/restore.py
transferchain/settings.py
transferchain/storage.py
transferchain/transaction.py
transferchain/transfer.py
transferchain/utils.py
transferchain/wallet.py
transferchain/crypt/__init__.py
transferchain/crypt/address.py
transferchain/crypt/bip39.py
transferchain/crypt/crypt.py
transferchain/crypt/keys.py
transferchain/crypt/words.py
transferchain/protobuf/__init__.py
transferchain/protobuf/service_pb2.py
transferchain/protobuf/service_pb2_grpc.py
transferchain_python_sdk-0.1.0.dist-info/LICENSE
transferchain_python_sdk-0.1.0.dist-info/METADATA
transferchain_python_sdk-0.1.0.dist-info/WHEEL
transferchain_python_sdk-0.1.0.dist-info/top_level.txt
transferchain_python_sdk-0.1.0.dist-info/RECORD
