Metadata-Version: 2.1
Name: transferchain-python-sdk
Version: 0.1.0
Summary: TransferChain Python SDK
Home-page: https://github.com/TransferChain/transferchain-python-sdk
Author: TransferChain
Author-email: info@transferchain.io
License: UNKNOWN
Platform: UNKNOWN
Requires-Python: >=3.8
License-File: LICENSE
Requires-Dist: PyNaCl (==1.5.0)
Requires-Dist: base58 (==2.1.1)
Requires-Dist: cryptography (==41.0.2)
Requires-Dist: ed25519 (==1.5)
Requires-Dist: grpcio-tools (==1.59.0)
Requires-Dist: grpcio (==1.59.0)
Requires-Dist: pickleDB (==0.9.2)
Requires-Dist: requests (==2.31.0)
Requires-Dist: tcabci-read-client
Requires-Dist: x25519 (==0.0.2)
